README.rst
setup.cfg
setup.py
aocxchange/__init__.py
aocxchange/brep.py
aocxchange/checks.py
aocxchange/dat.py
aocxchange/exceptions.py
aocxchange/extensions.py
aocxchange/iges.py
aocxchange/step.py
aocxchange/step_ocaf.py
aocxchange/stl.py
aocxchange/utils.py
aocxchange.egg-info/PKG-INFO
aocxchange.egg-info/SOURCES.txt
aocxchange.egg-info/dependency_links.txt
aocxchange.egg-info/requires.txt
aocxchange.egg-info/top_level.txt