Metadata-Version: 1.1
Name: aocxchange
Version: 0.3.0
Summary: Read/write to/from CAD files
Home-page: https://github.com/floatingpointstack/aoc-xchange
Author: Guillaume Florent
Author-email: florentsailing@gmail.com
License: GPL v3
Download-URL: https://github.com/floatingpointstack/aoc-xchange/releases/tag/0.3.0
Keywords: OpenCASCADE pythonocc CAD
Platform: UNKNOWN
Classifier: Development Status :: 3 - Alpha
Classifier: Intended Audience :: Developers
Classifier: Topic :: Software Development
Classifier: License :: OSI Approved :: GNU General Public License v3 (GPLv3)
Classifier: Programming Language :: Python :: 2
Classifier: Programming Language :: Python :: 2.7
Classifier: Programming Language :: Python :: 3
Classifier: Programming Language :: Python :: 3.2
Classifier: Programming Language :: Python :: 3.3
Classifier: Programming Language :: Python :: 3.4
